gixy/__init__.py
gixy/__main__.py
gixy/cli/__init__.py
gixy/cli/__main__.py
gixy/cli/argparser.py
gixy/cli/main.py
gixy/core/__init__.py
gixy/core/builtin_variables.py
gixy/core/config.py
gixy/core/context.py
gixy/core/exceptions.py
gixy/core/issue.py
gixy/core/manager.py
gixy/core/plugins_manager.py
gixy/core/regexp.py
gixy/core/severity.py
gixy/core/utils.py
gixy/core/variable.py
gixy/core/sre_parse/__init__.py
gixy/core/sre_parse/sre_constants.py
gixy/core/sre_parse/sre_parse.py
gixy/directives/__init__.py
gixy/directives/block.py
gixy/directives/directive.py
gixy/formatters/__init__.py
gixy/formatters/_jinja.py
gixy/formatters/base.py
gixy/formatters/checkstyle.py
gixy/formatters/console.py
gixy/formatters/json.py
gixy/formatters/rich_console.py
gixy/formatters/text.py
gixy/formatters/templates/console.j2
gixy/formatters/templates/text.j2
gixy/parser/__init__.py
gixy/parser/nginx_parser.py
gixy/parser/raw_parser.py
gixy/plugins/__init__.py
gixy/plugins/add_header_content_type.py
gixy/plugins/add_header_multiline.py
gixy/plugins/add_header_redefinition.py
gixy/plugins/alias_traversal.py
gixy/plugins/allow_without_deny.py
gixy/plugins/default_server_flag.py
gixy/plugins/error_log_off.py
gixy/plugins/hash_without_default.py
gixy/plugins/host_spoofing.py
gixy/plugins/hsts_header.py
gixy/plugins/http2_misdirected_request.py
gixy/plugins/http_splitting.py
gixy/plugins/if_is_evil.py
gixy/plugins/invalid_regex.py
gixy/plugins/low_keepalive_requests.py
gixy/plugins/missing_resolver.py
gixy/plugins/origins.py
gixy/plugins/plugin.py
gixy/plugins/proxy_pass_normalized.py
gixy/plugins/regex_redos.py
gixy/plugins/resolver_external.py
gixy/plugins/return_bypasses_allow_deny.py
gixy/plugins/ssrf.py
gixy/plugins/try_files_is_evil_too.py
gixy/plugins/unanchored_regex.py
gixy/plugins/valid_referers.py
gixy/plugins/version_disclosure.py
gixy/plugins/weak_ssl_tls.py
gixy/plugins/worker_rlimit_nofile_vs_connections.py
gixy/utils/__init__.py
gixy/utils/text.py
gixy_ng-0.2.29.dist-info/licenses/AUTHORS
gixy_ng-0.2.29.dist-info/licenses/LICENSE
gixy_ng-0.2.29.dist-info/METADATA
gixy_ng-0.2.29.dist-info/WHEEL
gixy_ng-0.2.29.dist-info/entry_points.txt
gixy_ng-0.2.29.dist-info/top_level.txt
gixy_ng-0.2.29.dist-info/RECORD
