Metadata-Version: 2.4
Name: gixy-ng
Version: 0.2.29
Summary: NGINX configuration [sec]analyzer
Home-page: https://github.com/dvershinin/gixy
Author: Yandex IS Team, GetPageSpeed LLC
Author-email: buglloc@yandex.ru, info@getpagespeed.com
Keywords: nginx security lint static-analysis
Classifier: Development Status :: 3 - Alpha
Classifier: Environment :: Console
Classifier: Intended Audience :: System Administrators
Classifier: Intended Audience :: Developers
Classifier: Topic :: Security
Classifier: Topic :: Software Development :: Quality Assurance
Classifier: Topic :: Software Development :: Testing
Classifier: Programming Language :: Python :: 3.6
Classifier: Programming Language :: Python :: 3.7
Classifier: Programming Language :: Python :: 3.8
Classifier: Programming Language :: Python :: 3.9
Classifier: Programming Language :: Python :: 3.10
Classifier: Programming Language :: Python :: 3.11
Classifier: Programming Language :: Python :: 3.12
Classifier: Programming Language :: Python :: 3.13
License-File: LICENSE
License-File: AUTHORS
Requires-Dist: ngxparse>=0.5.16
Requires-Dist: cached-property>=1.2.0; python_version < "3.8"
Requires-Dist: argparse>=1.4.0; python_version < "3.2"
Requires-Dist: Jinja2>=2.8
Requires-Dist: ConfigArgParse>=0.11.0
Provides-Extra: tests
Requires-Dist: ngxparse>=0.5.16; extra == "tests"
Requires-Dist: cached-property>=1.2.0; python_version < "3.8" and extra == "tests"
Requires-Dist: argparse>=1.4.0; python_version < "3.2" and extra == "tests"
Requires-Dist: Jinja2>=2.8; extra == "tests"
Requires-Dist: ConfigArgParse>=0.11.0; extra == "tests"
Requires-Dist: pytest>=7.0.0; extra == "tests"
Requires-Dist: pytest-xdist; extra == "tests"
Provides-Extra: rich
Requires-Dist: rich>=13.0.0; extra == "rich"
Provides-Extra: redos
Requires-Dist: requests>=2.20.0; extra == "redos"
Dynamic: author
Dynamic: author-email
Dynamic: classifier
Dynamic: description
Dynamic: description-content-type
Dynamic: home-page
Dynamic: keywords
Dynamic: license-file
Dynamic: provides-extra
Dynamic: requires-dist
Dynamic: summary
